minimal_molview/__init__.py
minimal_molview/_version.py
minimal_molview/py.typed
minimal_molview/render.py
minimal_molview/templates/InteractiveView.html
minimal_molview/templates/__init__.py
minimal_molview/templates/resources.py
minimal_molview/tests/__init__.py
minimal_molview/tests/test_minimal_molview.py
minimal_molview-0.2.0.dist-info/LICENSE
minimal_molview-0.2.0.dist-info/METADATA
minimal_molview-0.2.0.dist-info/WHEEL
minimal_molview-0.2.0.dist-info/entry_points.txt
minimal_molview-0.2.0.dist-info/top_level.txt
minimal_molview-0.2.0.dist-info/RECORD
