Metadata-Version: 2.1
Name: minimal_molview
Version: 0.2.0
Summary: A short description of the project (less than one line).
Author-email: Hugo MacDermottt-Opeskin <hugomacdermott@gmail.com>
License: MIT
Classifier: License :: OSI Approved :: MIT License
Classifier: Programming Language :: Python :: 3
Requires-Python: >=3.8
License-File: LICENSE
Requires-Dist: jinja2
Provides-Extra: test
Requires-Dist: pytest >=6.1.2 ; extra == 'test'
